cd_utils_file_to_sql/__init__.py
cd_utils_file_to_sql/fs_utils.py
cd_utils_file-1.0.1.dist-info/METADATA
cd_utils_file-1.0.1.dist-info/WHEEL
cd_utils_file-1.0.1.dist-info/top_level.txt
cd_utils_file-1.0.1.dist-info/RECORD
