Metadata-Version: 2.1
Name: cd-utils-file
Version: 1.0.1
Summary: Utilitário para manipulação de arquivo
Home-page: https://github.com/herculanocm/cd-utils-file
Author: Herculano Cunha
Author-email: herculanocm@outlook.com
License: MIT
Download-URL: https://github.com/herculanocm/cd-utils-file/archive/master.zip
Keywords: tools utils file
Platform: UNKNOWN
Classifier: Programming Language :: Python :: 3
Classifier: License :: OSI Approved :: MIT License
Classifier: Operating System :: OS Independent
Requires-Python: >=3
Requires-Dist: cd-utils-logger
